[{"id":"370ae1a4-263b-4d7f-b477-8e877d40e5e2","name":"Saumon","quantity":30.0,"unit":"GRAMS","addDate":[2024,11,28],"expirationDate":[2024,11,30]},{"id":"703f99e4-f785-44a3-b280-f1dbe37095f5","name":"Chicken","quantity":2.0,"unit":"KILOGRAMS","addDate":[2024,11,30],"expirationDate":[2024,12,5]},{"id":"3a5d3c4e-7da7-411f-86a2-7f4d791c4769","name":"Banane","quantity":21.0,"unit":"KILOGRAMS","addDate":[2024,11,29],"expirationDate":[2024,11,30]},{"id":"9fda00db-4563-40df-aff1-7cf0db171ba0","name":"Vegie","quantity":12.0,"unit":"KILOGRAMS","addDate":[2024,11,7],"expirationDate":[2024,12,17]},{"id":"5fea6900-75aa-42a8-91b0-000f950fcb1b","name":"Pork","quantity":1.1,"unit":"KILOGRAMS","addDate":[2024,11,28],"expirationDate":[2024,11,30]}]